<?xml version="1.0" encoding="UTF-8" standalone="yes"?>
<types>
    <type name="AmmoBox">
		<nominal>4</nominal>
		<lifetime>3888000</lifetime>
		<restock>14400</restock>
		<min>2</min>
		<quantmin>-1</quantmin>
		<quantmax>-1</quantmax>
		<cost>100</cost>
        <flags count_in_cargo="0" count_in_hoarder="0" count_in_map="1" count_in_player="0" crafted="0" deloot="1"/>
        <category name="containers"/>
        <usage name="Military"/>
    </type>
    <type name="Bear_Beige">
        <nominal>10</nominal>
        <lifetime>14400</lifetime>
        <restock>0</restock>
        <min>7</min>
        <quantmin>-1</quantmin>
        <quantmax>-1</quantmax>
        <cost>100</cost>
        <flags count_in_cargo="0" count_in_hoarder="0" count_in_map="1" count_in_player="0" crafted="0" deloot="0"/>
        <category name="containers"/>
        <tag name="shelves"/>
        <usage name="Town"/>
        <usage name="Village"/>
    </type>
    <type name="Bear_Dark">
        <nominal>10</nominal>
        <lifetime>14400</lifetime>
        <restock>0</restock>
        <min>7</min>
        <quantmin>-1</quantmin>
        <quantmax>-1</quantmax>
        <cost>100</cost>
        <flags count_in_cargo="0" count_in_hoarder="0" count_in_map="1" count_in_player="0" crafted="0" deloot="0"/>
        <category name="containers"/>
        <tag name="shelves"/>
        <usage name="Town"/>
        <usage name="Village"/>
    </type>
    <type name="Bear_Pink">
        <nominal>10</nominal>
        <lifetime>14400</lifetime>
        <restock>0</restock>
        <min>7</min>
        <quantmin>-1</quantmin>
        <quantmax>-1</quantmax>
        <cost>100</cost>
        <flags count_in_cargo="0" count_in_hoarder="0" count_in_map="1" count_in_player="0" crafted="0" deloot="0"/>
        <category name="containers"/>
        <tag name="shelves"/>
        <usage name="Town"/>
        <usage name="Village"/>
    </type>
    <type name="Bear_White">
        <nominal>10</nominal>
        <lifetime>14400</lifetime>
        <restock>0</restock>
        <min>7</min>
        <quantmin>-1</quantmin>
        <quantmax>-1</quantmax>
        <cost>100</cost>
        <flags count_in_cargo="0" count_in_hoarder="0" count_in_map="1" count_in_player="0" crafted="0" deloot="0"/>
        <category name="containers"/>
        <tag name="shelves"/>
        <usage name="Town"/>
        <usage name="Village"/>
    </type>
    <type name="CarTent">
		<nominal>3</nominal>
		<lifetime>3888000</lifetime>
		<restock>43200</restock>
		<min>2</min>
		<quantmin>-1</quantmin>
		<quantmax>-1</quantmax>
		<cost>100</cost>
        <flags count_in_cargo="1" count_in_hoarder="0" count_in_map="1" count_in_player="1" crafted="0" deloot="0"/>
        <category name="containers"/>
        <usage name="Industrial"/>
    </type>
    <type name="GiftBox_Large_1">
        <nominal>0</nominal>
        <lifetime>7200</lifetime>
        <restock>0</restock>
        <min>0</min>
        <quantmin>-1</quantmin>
        <quantmax>-1</quantmax>
        <cost>100</cost>
        <flags count_in_cargo="0" count_in_hoarder="0" count_in_map="1" count_in_player="0" crafted="0" deloot="0"/>
        <category name="containers"/>
        <tag name="floor"/>
        <tag name="shelves"/>
        <usage name="Town"/>
        <usage name="Village"/>
        <usage name="SeasonalEvent"/>
    </type>
    <type name="GiftBox_Large_2">
        <nominal>0</nominal>
        <lifetime>7200</lifetime>
        <restock>0</restock>
        <min>0</min>
        <quantmin>-1</quantmin>
        <quantmax>-1</quantmax>
        <cost>100</cost>
        <flags count_in_cargo="0" count_in_hoarder="0" count_in_map="1" count_in_player="0" crafted="0" deloot="0"/>
        <category name="containers"/>
        <tag name="floor"/>
        <tag name="shelves"/>
        <usage name="Town"/>
        <usage name="Village"/>
        <usage name="SeasonalEvent"/>
    </type>
    <type name="GiftBox_Large_3">
        <nominal>0</nominal>
        <lifetime>7200</lifetime>
        <restock>0</restock>
        <min>0</min>
        <quantmin>-1</quantmin>
        <quantmax>-1</quantmax>
        <cost>100</cost>
        <flags count_in_cargo="0" count_in_hoarder="0" count_in_map="1" count_in_player="0" crafted="0" deloot="0"/>
        <category name="containers"/>
        <tag name="floor"/>
        <tag name="shelves"/>
        <usage name="Town"/>
        <usage name="Village"/>
        <usage name="SeasonalEvent"/>
    </type>
    <type name="GiftBox_Large_4">
        <nominal>0</nominal>
        <lifetime>7200</lifetime>
        <restock>0</restock>
        <min>0</min>
        <quantmin>-1</quantmin>
        <quantmax>-1</quantmax>
        <cost>100</cost>
        <flags count_in_cargo="0" count_in_hoarder="0" count_in_map="1" count_in_player="0" crafted="0" deloot="0"/>
        <category name="containers"/>
        <tag name="floor"/>
        <tag name="shelves"/>
        <usage name="Town"/>
        <usage name="Village"/>
        <usage name="SeasonalEvent"/>
    </type>
    <type name="GiftBox_Medium_1">
        <nominal>0</nominal>
        <lifetime>7200</lifetime>
        <restock>0</restock>
        <min>0</min>
        <quantmin>-1</quantmin>
        <quantmax>-1</quantmax>
        <cost>100</cost>
        <flags count_in_cargo="0" count_in_hoarder="0" count_in_map="1" count_in_player="0" crafted="0" deloot="0"/>
        <category name="containers"/>
        <tag name="floor"/>
        <tag name="shelves"/>
        <usage name="Town"/>
        <usage name="Village"/>
        <usage name="SeasonalEvent"/>
    </type>
    <type name="GiftBox_Medium_2">
        <nominal>0</nominal>
        <lifetime>7200</lifetime>
        <restock>0</restock>
        <min>0</min>
        <quantmin>-1</quantmin>
        <quantmax>-1</quantmax>
        <cost>100</cost>
        <flags count_in_cargo="0" count_in_hoarder="0" count_in_map="1" count_in_player="0" crafted="0" deloot="0"/>
        <category name="containers"/>
        <tag name="floor"/>
        <tag name="shelves"/>
        <usage name="Town"/>
        <usage name="Village"/>
        <usage name="SeasonalEvent"/>
    </type>
    <type name="GiftBox_Medium_3">
        <nominal>0</nominal>
        <lifetime>7200</lifetime>
        <restock>0</restock>
        <min>0</min>
        <quantmin>-1</quantmin>
        <quantmax>-1</quantmax>
        <cost>100</cost>
        <flags count_in_cargo="0" count_in_hoarder="0" count_in_map="1" count_in_player="0" crafted="0" deloot="0"/>
        <category name="containers"/>
        <tag name="floor"/>
        <tag name="shelves"/>
        <usage name="Town"/>
        <usage name="Village"/>
        <usage name="SeasonalEvent"/>
    </type>
    <type name="GiftBox_Medium_4">
        <nominal>0</nominal>
        <lifetime>7200</lifetime>
        <restock>0</restock>
        <min>0</min>
        <quantmin>-1</quantmin>
        <quantmax>-1</quantmax>
        <cost>100</cost>
        <flags count_in_cargo="0" count_in_hoarder="0" count_in_map="1" count_in_player="0" crafted="0" deloot="0"/>
        <category name="containers"/>
        <tag name="floor"/>
        <tag name="shelves"/>
        <usage name="Town"/>
        <usage name="Village"/>
        <usage name="SeasonalEvent"/>
    </type>
    <type name="GiftBox_Small_1">
        <nominal>0</nominal>
        <lifetime>7200</lifetime>
        <restock>0</restock>
        <min>0</min>
        <quantmin>-1</quantmin>
        <quantmax>-1</quantmax>
        <cost>100</cost>
        <flags count_in_cargo="0" count_in_hoarder="0" count_in_map="1" count_in_player="0" crafted="0" deloot="0"/>
        <category name="containers"/>
        <tag name="floor"/>
        <tag name="shelves"/>
        <usage name="Town"/>
        <usage name="Village"/>
        <usage name="SeasonalEvent"/>
    </type>
    <type name="GiftBox_Small_2">
        <nominal>0</nominal>
        <lifetime>7200</lifetime>
        <restock>0</restock>
        <min>0</min>
        <quantmin>-1</quantmin>
        <quantmax>-1</quantmax>
        <cost>100</cost>
        <flags count_in_cargo="0" count_in_hoarder="0" count_in_map="1" count_in_player="0" crafted="0" deloot="0"/>
        <category name="containers"/>
        <tag name="floor"/>
        <tag name="shelves"/>
        <usage name="Town"/>
        <usage name="Village"/>
        <usage name="SeasonalEvent"/>
    </type>
    <type name="GiftBox_Small_3">
        <nominal>0</nominal>
        <lifetime>7200</lifetime>
        <restock>0</restock>
        <min>0</min>
        <quantmin>-1</quantmin>
        <quantmax>-1</quantmax>
        <cost>100</cost>
        <flags count_in_cargo="0" count_in_hoarder="0" count_in_map="1" count_in_player="0" crafted="0" deloot="0"/>
        <category name="containers"/>
        <tag name="floor"/>
        <tag name="shelves"/>
        <usage name="Town"/>
        <usage name="Village"/>
        <usage name="SeasonalEvent"/>
    </type>
    <type name="GiftBox_Small_4">
        <nominal>0</nominal>
        <lifetime>7200</lifetime>
        <restock>0</restock>
        <min>0</min>
        <quantmin>-1</quantmin>
        <quantmax>-1</quantmax>
        <cost>100</cost>
        <flags count_in_cargo="0" count_in_hoarder="0" count_in_map="1" count_in_player="0" crafted="0" deloot="0"/>
        <category name="containers"/>
        <tag name="floor"/>
        <tag name="shelves"/>
        <usage name="Town"/>
        <usage name="Village"/>
        <usage name="SeasonalEvent"/>
    </type>
    <type name="LargeTent">
		<nominal>3</nominal>
		<lifetime>3888000</lifetime>
		<restock>43200</restock>
		<min>2</min>
		<quantmin>-1</quantmin>
		<quantmax>-1</quantmax>
		<cost>100</cost>
        <flags count_in_cargo="1" count_in_hoarder="0" count_in_map="1" count_in_player="1" crafted="0" deloot="0"/>
        <category name="containers"/>
        <usage name="Military"/>
    </type>
    <type name="MediumTent">
		<nominal>3</nominal>
		<lifetime>3888000</lifetime>
		<restock>43200</restock>
		<min>2</min>
		<quantmin>-1</quantmin>
		<quantmax>-1</quantmax>
		<cost>100</cost>
        <flags count_in_cargo="1" count_in_hoarder="0" count_in_map="1" count_in_player="1" crafted="0" deloot="0"/>
        <category name="containers"/>
        <usage name="Town"/>
        <usage name="Village"/>
    </type>
    <type name="MediumTent_Green">
		<nominal>3</nominal>
		<lifetime>3888000</lifetime>
		<restock>43200</restock>
		<min>2</min>
		<quantmin>-1</quantmin>
		<quantmax>-1</quantmax>
		<cost>100</cost>
        <flags count_in_cargo="1" count_in_hoarder="1" count_in_map="1" count_in_player="1" crafted="0" deloot="0"/>
        <category name="containers"/>
        <usage name="Village"/>
        <usage name="Hunting"/>
    </type>
    <type name="MediumTent_Orange">
		<nominal>3</nominal>
		<lifetime>3888000</lifetime>
		<restock>43200</restock>
		<min>2</min>
		<quantmin>-1</quantmin>
		<quantmax>-1</quantmax>
		<cost>100</cost>
        <flags count_in_cargo="1" count_in_hoarder="1" count_in_map="1" count_in_player="1" crafted="0" deloot="0"/>
        <category name="containers"/>
        <usage name="Town"/>
        <usage name="Village"/>
    </type>
    <type name="PartyTent">
		<nominal>3</nominal>
		<lifetime>3888000</lifetime>
		<restock>43200</restock>
		<min>2</min>
		<quantmin>-1</quantmin>
		<quantmax>-1</quantmax>
		<cost>100</cost>
        <flags count_in_cargo="1" count_in_hoarder="1" count_in_map="1" count_in_player="1" crafted="0" deloot="0"/>
        <category name="containers"/>
        <usage name="Town"/>
    </type>
    <type name="PartyTent_Blue">
		<nominal>3</nominal>
		<lifetime>3888000</lifetime>
		<restock>43200</restock>
		<min>2</min>
		<quantmin>-1</quantmin>
		<quantmax>-1</quantmax>
		<cost>100</cost>
        <flags count_in_cargo="1" count_in_hoarder="1" count_in_map="1" count_in_player="1" crafted="0" deloot="0"/>
        <category name="containers"/>
        <usage name="Town"/>
    </type>
    <type name="PartyTent_Brown">
		<nominal>3</nominal>
		<lifetime>3888000</lifetime>
		<restock>43200</restock>
		<min>2</min>
		<quantmin>-1</quantmin>
		<quantmax>-1</quantmax>
		<cost>100</cost>
        <flags count_in_cargo="1" count_in_hoarder="1" count_in_map="1" count_in_player="1" crafted="0" deloot="0"/>
        <category name="containers"/>
        <usage name="Town"/>
    </type>
    <type name="PartyTent_Lunapark">
		<nominal>3</nominal>
		<lifetime>3888000</lifetime>
		<restock>43200</restock>
		<min>2</min>
		<quantmin>-1</quantmin>
		<quantmax>-1</quantmax>
		<cost>100</cost>
        <flags count_in_cargo="1" count_in_hoarder="1" count_in_map="1" count_in_player="1" crafted="0" deloot="0"/>
        <category name="containers"/>
        <usage name="Lunapark"/>
    </type>
    <type name="SeaChest">
		<nominal>5</nominal>
		<lifetime>3888000</lifetime>
		<restock>1200</restock>
		<min>4</min>
		<quantmin>-1</quantmin>
		<quantmax>-1</quantmax>
		<cost>100</cost>
        <flags count_in_cargo="0" count_in_hoarder="0" count_in_map="1" count_in_player="1" crafted="0" deloot="0"/>
        <category name="tools"/>
        <usage name="Industrial"/>
        <usage name="Farm"/>
        <usage name="Coast"/>
        <usage name="Hunting"/>
    </type>
    <type name="ShelterFabric">
        <nominal>0</nominal>
        <lifetime>604800</lifetime>
        <restock>0</restock>
        <min>0</min>
        <quantmin>-1</quantmin>
        <quantmax>-1</quantmax>
        <cost>100</cost>
        <flags count_in_cargo="0" count_in_hoarder="0" count_in_map="1" count_in_player="0" crafted="1" deloot="0"/>
        <category name="containers"/>
    </type>
    <type name="ShelterLeather">
        <nominal>0</nominal>
        <lifetime>604800</lifetime>
        <restock>0</restock>
        <min>0</min>
        <quantmin>-1</quantmin>
        <quantmax>-1</quantmax>
        <cost>100</cost>
        <flags count_in_cargo="0" count_in_hoarder="0" count_in_map="1" count_in_player="0" crafted="1" deloot="0"/>
        <category name="containers"/>
    </type>
    <type name="ShelterStick">
        <nominal>0</nominal>
        <lifetime>604800</lifetime>
        <restock>0</restock>
        <min>0</min>
        <quantmin>-1</quantmin>
        <quantmax>-1</quantmax>
        <cost>100</cost>
        <flags count_in_cargo="0" count_in_hoarder="0" count_in_map="1" count_in_player="0" crafted="1" deloot="0"/>
        <category name="containers"/>
    </type>
    <type name="SmallProtectorCase">
		<nominal>25</nominal>
		<lifetime>3888000</lifetime>
		<restock>0</restock>
		<min>20</min>
		<quantmin>-1</quantmin>
		<quantmax>-1</quantmax>
		<cost>100</cost>
        <flags count_in_cargo="0" count_in_hoarder="0" count_in_map="1" count_in_player="0" crafted="0" deloot="0"/>
        <category name="containers"/>
        <usage name="Industrial"/>
        <usage name="Town"/>
    </type>
    <type name="UndergroundStash">
        <nominal>0</nominal>
        <lifetime>1209600</lifetime>
        <restock>0</restock>
        <min>0</min>
        <quantmin>-1</quantmin>
        <quantmax>-1</quantmax>
        <cost>100</cost>
        <flags count_in_cargo="0" count_in_hoarder="0" count_in_map="1" count_in_player="0" crafted="1" deloot="0"/>
        <category name="containers"/>
    </type>
    <type name="WaterproofBag_Green">
		<nominal>10</nominal>
		<lifetime>28800</lifetime>
		<restock>1200</restock>
		<min>5</min>
		<quantmin>-1</quantmin>
		<quantmax>-1</quantmax>
		<cost>100</cost>
        <flags count_in_cargo="0" count_in_hoarder="0" count_in_map="1" count_in_player="0" crafted="0" deloot="0"/>
        <category name="containers"/>
        <usage name="Coast"/>
    </type>
    <type name="WaterproofBag_Orange">
		<nominal>10</nominal>
		<lifetime>28800</lifetime>
		<restock>1200</restock>
		<min>5</min>
		<quantmin>-1</quantmin>
		<quantmax>-1</quantmax>
		<cost>100</cost>
        <flags count_in_cargo="0" count_in_hoarder="0" count_in_map="1" count_in_player="0" crafted="0" deloot="0"/>
        <category name="containers"/>
        <usage name="Coast"/>
    </type>
    <type name="WaterproofBag_Yellow">
		<nominal>10</nominal>
		<lifetime>28800</lifetime>
		<restock>1200</restock>
		<min>5</min>
		<quantmin>-1</quantmin>
		<quantmax>-1</quantmax>
		<cost>100</cost>
        <flags count_in_cargo="0" count_in_hoarder="0" count_in_map="1" count_in_player="0" crafted="0" deloot="0"/>
        <category name="containers"/>
        <usage name="Coast"/>
    </type>
    <type name="WoodenCrate">
        <nominal>0</nominal>
        <lifetime>3888000</lifetime>
        <restock>0</restock>
        <min>0</min>
        <quantmin>-1</quantmin>
        <quantmax>-1</quantmax>
        <cost>100</cost>
        <flags count_in_cargo="0" count_in_hoarder="0" count_in_map="1" count_in_player="0" crafted="1" deloot="0"/>
        <category name="containers"/>
    </type>


</types>
